simpleml/__init__.py
simpleml/metrics/__init__.py
simpleml/metrics/classification.py
simpleml/model_selection/__init__.py
simpleml/model_selection/cross_validation.py
simpleml/models/__init__.py
simpleml/models/decision_tree.py
simpleml/models/knn_classifier.py
simpleml/models/linear_regression.py
simpleml/pipeline/__init__.py
simpleml/pipeline/pipeline.py
simpleml/preprocessing/__init__.py
simpleml/utils/__init__.py
simpleml/utils/io.py
simpleml/utils/train_test_split.py
simpleml_aaditya025-0.1.0.dist-info/METADATA
simpleml_aaditya025-0.1.0.dist-info/WHEEL
simpleml_aaditya025-0.1.0.dist-info/top_level.txt
simpleml_aaditya025-0.1.0.dist-info/RECORD
